Jupytils/Charts.py
Jupytils/ChartsOld.py
Jupytils/Classification.py
Jupytils/Clustering.py
Jupytils/DBUtils.py
Jupytils/DataFrameUtils.py
Jupytils/DisplayUtils.py
Jupytils/ExcelFormulas.ipynb
Jupytils/ExcelUtils.ipynb
Jupytils/Features.py
Jupytils/FlaskSQLWS.py
Jupytils/License.txt
Jupytils/Map.py
Jupytils/README.rst
Jupytils/ShowExcel.ipynb
Jupytils/StatUtils.py
Jupytils/__init__.py
Jupytils/ajax.html
Jupytils/csv1.py
Jupytils/jcommon.ipynb
Jupytils/jcommon.py
Jupytils/test1.xlsx
Jupytils/test2.xlsx
Jupytils/version.txt
Jupytils-0.41100000000000003.dist-info/METADATA
Jupytils-0.41100000000000003.dist-info/RECORD
Jupytils-0.41100000000000003.dist-info/WHEEL
Jupytils-0.41100000000000003.dist-info/top_level.txt
