Metadata-Version: 2.1
Name: Jupytils
Version: 0.41100000000000003
Summary: Productive Simple Intuitive Jupyter Python Utilities
Home-page: https://github.com/sada-narayanappa/PyUtils.git
Author: Code Red
Author-email: sada@geospaces.org
License: MIT
Platform: UNKNOWN
Classifier: Development Status :: 3 - Alpha
Classifier: Intended Audience :: Developers
Classifier: License :: OSI Approved :: MIT License
Classifier: Programming Language :: Python :: 3
Classifier: Programming Language :: Python :: 3.2
Classifier: Programming Language :: Python :: 3.3
Classifier: Programming Language :: Python :: 3.4
Classifier: Programming Language :: Python :: 3.5
Classifier: Programming Language :: Python :: 3.6
Classifier: Programming Language :: Python :: 3.7
Requires-Dist: matplotlib
Requires-Dist: openpyxl
